[
  {
    "IsVisible": true,
    "Book": "OT2_About",
    "Name": "About This Edition",
    "XPath": "/html[1]/body[@book='OT2_About']/book",
    "Children": []
  },
  {
    "IsVisible": true,
    "Book": "OT2_ChronologyKings",
    "Name": "Chronology of Kings",
    "XPath": "/html[1]/body[@book='OT2_ChronologyKings']/book",
    "Children": []
  },
  {
    "IsVisible": true,
    "Book": "OT2_1Samuel",
    "Name": "1 Samuel",
    "XPath": "/html[1]/body[@book='OT2_1Samuel']/book",
    "Children": [
      {
        "IsVisible": true,
        "Book": "OT2_1Samuel",
        "Name": "1 Samuel 1",
        "XPath": "(/html[1]/body[@book='OT2_1Samuel']//chapter)[1]",
        "Children": []
      },
      {
        "IsVisible": true,
        "Book": "OT2_1Samuel",
        "Name": "1 Samuel 2",
        "XPath": "(/html[1]/body[@book='OT2_1Samuel']//chapter)[2]",
        "Children": []
      },
      {
        "IsVisible": true,
        "Book": "OT2_1Samuel",
        "Name": "1 Samuel 3",
        "XPath": "(/html[1]/body[@book='OT2_1Samuel']//chapter)[3]",
        "Children": []
      },
      {
        "IsVisible": true,
        "Book": "OT2_1Samuel",
        "Name": "1 Samuel 4",
        "XPath": "(/html[1]/body[@book='OT2_1Samuel']//chapter)[4]",
        "Children": []
      },
      {
        "IsVisible": true,
        "Book": "OT2_1Samuel",
        "Name": "1 Samuel 5",
        "XPath": "(/html[1]/body[@book='OT2_1Samuel']//chapter)[5]",
        "Children": []
      },
      {
        "IsVisible": true,
        "Book": "OT2_1Samuel",
        "Name": "1 Samuel 6",
        "XPath": "(/html[1]/body[@book='OT2_1Samuel']//chapter)[6]",
        "Children": []
      },
      {
        "IsVisible": true,
        "Book": "OT2_1Samuel",
        "Name": "1 Samuel 7",
        "XPath": "(/html[1]/body[@book='OT2_1Samuel']//chapter)[7]",
        "Children": []
      },
      {
        "IsVisible": true,
        "Book": "OT2_1Samuel",
        "Name": "1 Samuel 8",
        "XPath": "(/html[1]/body[@book='OT2_1Samuel']//chapter)[8]",
        "Children": []
      },
      {
        "IsVisible": true,
        "Book": "OT2_1Samuel",
        "Name": "1 Samuel 9",
        "XPath": "(/html[1]/body[@book='OT2_1Samuel']//chapter)[9]",
        "Children": []
      },
      {
        "IsVisible": true,
        "Book": "OT2_1Samuel",
        "Name": "1 Samuel 10",
        "XPath": "(/html[1]/body[@book='OT2_1Samuel']//chapter)[10]",
        "Children": []
      },
      {
        "IsVisible": true,
        "Book": "OT2_1Samuel",
        "Name": "1 Samuel 11",
        "XPath": "(/html[1]/body[@book='OT2_1Samuel']//chapter)[11]",
        "Children": []
      },
      {
        "IsVisible": true,
        "Book": "OT2_1Samuel",
        "Name": "1 Samuel 12",
        "XPath": "(/html[1]/body[@book='OT2_1Samuel']//chapter)[12]",
        "Children": []
      },
      {
        "IsVisible": true,
        "Book": "OT2_1Samuel",
        "Name": "1 Samuel 13",
        "XPath": "(/html[1]/body[@book='OT2_1Samuel']//chapter)[13]",
        "Children": []
      },
      {
        "IsVisible": true,
        "Book": "OT2_1Samuel",
        "Name": "1 Samuel 14",
        "XPath": "(/html[1]/body[@book='OT2_1Samuel']//chapter)[14]",
        "Children": []
      },
      {
        "IsVisible": true,
        "Book": "OT2_1Samuel",
        "Name": "1 Samuel 15",
        "XPath": "(/html[1]/body[@book='OT2_1Samuel']//chapter)[15]",
        "Children": []
      },
      {
        "IsVisible": true,
        "Book": "OT2_1Samuel",
        "Name": "1 Samuel 16",
        "XPath": "(/html[1]/body[@book='OT2_1Samuel']//chapter)[16]",
        "Children": []
      },
      {
        "IsVisible": true,
        "Book": "OT2_1Samuel",
        "Name": "1 Samuel 17",
        "XPath": "(/html[1]/body[@book='OT2_1Samuel']//chapter)[17]",
        "Children": []
      },
      {
        "IsVisible": true,
        "Book": "OT2_1Samuel",
        "Name": "1 Samuel 18",
        "XPath": "(/html[1]/body[@book='OT2_1Samuel']//chapter)[18]",
        "Children": []
      },
      {
        "IsVisible": true,
        "Book": "OT2_1Samuel",
        "Name": "1 Samuel 19",
        "XPath": "(/html[1]/body[@book='OT2_1Samuel']//chapter)[19]",
        "Children": []
      },
      {
        "IsVisible": true,
        "Book": "OT2_1Samuel",
        "Name": "1 Samuel 20",
        "XPath": "(/html[1]/body[@book='OT2_1Samuel']//chapter)[20]",
        "Children": []
      },
      {
        "IsVisible": true,
        "Book": "OT2_1Samuel",
        "Name": "1 Samuel 21",
        "XPath": "(/html[1]/body[@book='OT2_1Samuel']//chapter)[21]",
        "Children": []
      },
      {
        "IsVisible": true,
        "Book": "OT2_1Samuel",
        "Name": "1 Samuel 22",
        "XPath": "(/html[1]/body[@book='OT2_1Samuel']//chapter)[22]",
        "Children": []
      },
      {
        "IsVisible": true,
        "Book": "OT2_1Samuel",
        "Name": "1 Samuel 23",
        "XPath": "(/html[1]/body[@book='OT2_1Samuel']//chapter)[23]",
        "Children": []
      },
      {
        "IsVisible": true,
        "Book": "OT2_1Samuel",
        "Name": "1 Samuel 24",
        "XPath": "(/html[1]/body[@book='OT2_1Samuel']//chapter)[24]",
        "Children": []
      },
      {
        "IsVisible": true,
        "Book": "OT2_1Samuel",
        "Name": "1 Samuel 25",
        "XPath": "(/html[1]/body[@book='OT2_1Samuel']//chapter)[25]",
        "Children": []
      },
      {
        "IsVisible": true,
        "Book": "OT2_1Samuel",
        "Name": "1 Samuel 26",
        "XPath": "(/html[1]/body[@book='OT2_1Samuel']//chapter)[26]",
        "Children": []
      },
      {
        "IsVisible": true,
        "Book": "OT2_1Samuel",
        "Name": "1 Samuel 27",
        "XPath": "(/html[1]/body[@book='OT2_1Samuel']//chapter)[27]",
        "Children": []
      },
      {
        "IsVisible": true,
        "Book": "OT2_1Samuel",
        "Name": "1 Samuel 28",
        "XPath": "(/html[1]/body[@book='OT2_1Samuel']//chapter)[28]",
        "Children": []
      },
      {
        "IsVisible": true,
        "Book": "OT2_1Samuel",
        "Name": "1 Samuel 29",
        "XPath": "(/html[1]/body[@book='OT2_1Samuel']//chapter)[29]",
        "Children": []
      },
      {
        "IsVisible": true,
        "Book": "OT2_1Samuel",
        "Name": "1 Samuel 30",
        "XPath": "(/html[1]/body[@book='OT2_1Samuel']//chapter)[30]",
        "Children": []
      },
      {
        "IsVisible": true,
        "Book": "OT2_1Samuel",
        "Name": "1 Samuel 31",
        "XPath": "(/html[1]/body[@book='OT2_1Samuel']//chapter)[31]",
        "Children": []
      }
    ]
  },
  {
    "IsVisible": true,
    "Book": "OT2_2Samuel",
    "Name": "2 Samuel",
    "XPath": "/html[1]/body[@book='OT2_2Samuel']/book",
    "Children": [
      {
        "IsVisible": true,
        "Book": "OT2_2Samuel",
        "Name": "2 Samuel 1",
        "XPath": "(/html[1]/body[@book='OT2_2Samuel']//chapter)[1]",
        "Children": []
      },
      {
        "IsVisible": true,
        "Book": "OT2_2Samuel",
        "Name": "2 Samuel 2",
        "XPath": "(/html[1]/body[@book='OT2_2Samuel']//chapter)[2]",
        "Children": []
      },
      {
        "IsVisible": true,
        "Book": "OT2_2Samuel",
        "Name": "2 Samuel 3",
        "XPath": "(/html[1]/body[@book='OT2_2Samuel']//chapter)[3]",
        "Children": []
      },
      {
        "IsVisible": true,
        "Book": "OT2_2Samuel",
        "Name": "2 Samuel 4",
        "XPath": "(/html[1]/body[@book='OT2_2Samuel']//chapter)[4]",
        "Children": []
      },
      {
        "IsVisible": true,
        "Book": "OT2_2Samuel",
        "Name": "2 Samuel 5",
        "XPath": "(/html[1]/body[@book='OT2_2Samuel']//chapter)[5]",
        "Children": []
      },
      {
        "IsVisible": true,
        "Book": "OT2_2Samuel",
        "Name": "2 Samuel 6",
        "XPath": "(/html[1]/body[@book='OT2_2Samuel']//chapter)[6]",
        "Children": []
      },
      {
        "IsVisible": true,
        "Book": "OT2_2Samuel",
        "Name": "2 Samuel 7",
        "XPath": "(/html[1]/body[@book='OT2_2Samuel']//chapter)[7]",
        "Children": []
      },
      {
        "IsVisible": true,
        "Book": "OT2_2Samuel",
        "Name": "2 Samuel 8",
        "XPath": "(/html[1]/body[@book='OT2_2Samuel']//chapter)[8]",
        "Children": []
      },
      {
        "IsVisible": true,
        "Book": "OT2_2Samuel",
        "Name": "2 Samuel 9",
        "XPath": "(/html[1]/body[@book='OT2_2Samuel']//chapter)[9]",
        "Children": []
      },
      {
        "IsVisible": true,
        "Book": "OT2_2Samuel",
        "Name": "2 Samuel 10",
        "XPath": "(/html[1]/body[@book='OT2_2Samuel']//chapter)[10]",
        "Children": []
      },
      {
        "IsVisible": true,
        "Book": "OT2_2Samuel",
        "Name": "2 Samuel 11",
        "XPath": "(/html[1]/body[@book='OT2_2Samuel']//chapter)[11]",
        "Children": []
      },
      {
        "IsVisible": true,
        "Book": "OT2_2Samuel",
        "Name": "2 Samuel 12",
        "XPath": "(/html[1]/body[@book='OT2_2Samuel']//chapter)[12]",
        "Children": []
      },
      {
        "IsVisible": true,
        "Book": "OT2_2Samuel",
        "Name": "2 Samuel 13",
        "XPath": "(/html[1]/body[@book='OT2_2Samuel']//chapter)[13]",
        "Children": []
      },
      {
        "IsVisible": true,
        "Book": "OT2_2Samuel",
        "Name": "2 Samuel 14",
        "XPath": "(/html[1]/body[@book='OT2_2Samuel']//chapter)[14]",
        "Children": []
      },
      {
        "IsVisible": true,
        "Book": "OT2_2Samuel",
        "Name": "2 Samuel 15",
        "XPath": "(/html[1]/body[@book='OT2_2Samuel']//chapter)[15]",
        "Children": []
      },
      {
        "IsVisible": true,
        "Book": "OT2_2Samuel",
        "Name": "2 Samuel 16",
        "XPath": "(/html[1]/body[@book='OT2_2Samuel']//chapter)[16]",
        "Children": []
      },
      {
        "IsVisible": true,
        "Book": "OT2_2Samuel",
        "Name": "2 Samuel 17",
        "XPath": "(/html[1]/body[@book='OT2_2Samuel']//chapter)[17]",
        "Children": []
      },
      {
        "IsVisible": true,
        "Book": "OT2_2Samuel",
        "Name": "2 Samuel 18",
        "XPath": "(/html[1]/body[@book='OT2_2Samuel']//chapter)[18]",
        "Children": []
      },
      {
        "IsVisible": true,
        "Book": "OT2_2Samuel",
        "Name": "2 Samuel 19",
        "XPath": "(/html[1]/body[@book='OT2_2Samuel']//chapter)[19]",
        "Children": []
      },
      {
        "IsVisible": true,
        "Book": "OT2_2Samuel",
        "Name": "2 Samuel 20",
        "XPath": "(/html[1]/body[@book='OT2_2Samuel']//chapter)[20]",
        "Children": []
      },
      {
        "IsVisible": true,
        "Book": "OT2_2Samuel",
        "Name": "2 Samuel 21",
        "XPath": "(/html[1]/body[@book='OT2_2Samuel']//chapter)[21]",
        "Children": []
      },
      {
        "IsVisible": true,
        "Book": "OT2_2Samuel",
        "Name": "2 Samuel 22",
        "XPath": "(/html[1]/body[@book='OT2_2Samuel']//chapter)[22]",
        "Children": []
      },
      {
        "IsVisible": true,
        "Book": "OT2_2Samuel",
        "Name": "2 Samuel 23",
        "XPath": "(/html[1]/body[@book='OT2_2Samuel']//chapter)[23]",
        "Children": []
      },
      {
        "IsVisible": true,
        "Book": "OT2_2Samuel",
        "Name": "2 Samuel 24",
        "XPath": "(/html[1]/body[@book='OT2_2Samuel']//chapter)[24]",
        "Children": []
      }
    ]
  },
  {
    "IsVisible": true,
    "Book": "OT2_1Kings",
    "Name": "1 Kings",
    "XPath": "/html[1]/body[@book='OT2_1Kings']/book",
    "Children": [
      {
        "IsVisible": true,
        "Book": "OT2_1Kings",
        "Name": "1 Kings 1",
        "XPath": "(/html[1]/body[@book='OT2_1Kings']//chapter)[1]",
        "Children": []
      },
      {
        "IsVisible": true,
        "Book": "OT2_1Kings",
        "Name": "1 Kings 2",
        "XPath": "(/html[1]/body[@book='OT2_1Kings']//chapter)[2]",
        "Children": []
      },
      {
        "IsVisible": true,
        "Book": "OT2_1Kings",
        "Name": "1 Kings 3",
        "XPath": "(/html[1]/body[@book='OT2_1Kings']//chapter)[3]",
        "Children": []
      },
      {
        "IsVisible": true,
        "Book": "OT2_1Kings",
        "Name": "1 Kings 4",
        "XPath": "(/html[1]/body[@book='OT2_1Kings']//chapter)[4]",
        "Children": []
      },
      {
        "IsVisible": true,
        "Book": "OT2_1Kings",
        "Name": "1 Kings 5",
        "XPath": "(/html[1]/body[@book='OT2_1Kings']//chapter)[5]",
        "Children": []
      },
      {
        "IsVisible": true,
        "Book": "OT2_1Kings",
        "Name": "1 Kings 6",
        "XPath": "(/html[1]/body[@book='OT2_1Kings']//chapter)[6]",
        "Children": []
      },
      {
        "IsVisible": true,
        "Book": "OT2_1Kings",
        "Name": "1 Kings 7",
        "XPath": "(/html[1]/body[@book='OT2_1Kings']//chapter)[7]",
        "Children": []
      },
      {
        "IsVisible": true,
        "Book": "OT2_1Kings",
        "Name": "1 Kings 8",
        "XPath": "(/html[1]/body[@book='OT2_1Kings']//chapter)[8]",
        "Children": []
      },
      {
        "IsVisible": true,
        "Book": "OT2_1Kings",
        "Name": "1 Kings 9",
        "XPath": "(/html[1]/body[@book='OT2_1Kings']//chapter)[9]",
        "Children": []
      },
      {
        "IsVisible": true,
        "Book": "OT2_1Kings",
        "Name": "1 Kings 10",
        "XPath": "(/html[1]/body[@book='OT2_1Kings']//chapter)[10]",
        "Children": []
      },
      {
        "IsVisible": true,
        "Book": "OT2_1Kings",
        "Name": "1 Kings 11",
        "XPath": "(/html[1]/body[@book='OT2_1Kings']//chapter)[11]",
        "Children": []
      },
      {
        "IsVisible": true,
        "Book": "OT2_1Kings",
        "Name": "1 Kings 12",
        "XPath": "(/html[1]/body[@book='OT2_1Kings']//chapter)[12]",
        "Children": []
      },
      {
        "IsVisible": true,
        "Book": "OT2_1Kings",
        "Name": "1 Kings 13",
        "XPath": "(/html[1]/body[@book='OT2_1Kings']//chapter)[13]",
        "Children": []
      },
      {
        "IsVisible": true,
        "Book": "OT2_1Kings",
        "Name": "1 Kings 14",
        "XPath": "(/html[1]/body[@book='OT2_1Kings']//chapter)[14]",
        "Children": []
      },
      {
        "IsVisible": true,
        "Book": "OT2_1Kings",
        "Name": "1 Kings 15",
        "XPath": "(/html[1]/body[@book='OT2_1Kings']//chapter)[15]",
        "Children": []
      },
      {
        "IsVisible": true,
        "Book": "OT2_1Kings",
        "Name": "1 Kings 16",
        "XPath": "(/html[1]/body[@book='OT2_1Kings']//chapter)[16]",
        "Children": []
      },
      {
        "IsVisible": true,
        "Book": "OT2_1Kings",
        "Name": "1 Kings 17",
        "XPath": "(/html[1]/body[@book='OT2_1Kings']//chapter)[17]",
        "Children": []
      },
      {
        "IsVisible": true,
        "Book": "OT2_1Kings",
        "Name": "1 Kings 18",
        "XPath": "(/html[1]/body[@book='OT2_1Kings']//chapter)[18]",
        "Children": []
      },
      {
        "IsVisible": true,
        "Book": "OT2_1Kings",
        "Name": "1 Kings 19",
        "XPath": "(/html[1]/body[@book='OT2_1Kings']//chapter)[19]",
        "Children": []
      },
      {
        "IsVisible": true,
        "Book": "OT2_1Kings",
        "Name": "1 Kings 20",
        "XPath": "(/html[1]/body[@book='OT2_1Kings']//chapter)[20]",
        "Children": []
      },
      {
        "IsVisible": true,
        "Book": "OT2_1Kings",
        "Name": "1 Kings 21",
        "XPath": "(/html[1]/body[@book='OT2_1Kings']//chapter)[21]",
        "Children": []
      },
      {
        "IsVisible": true,
        "Book": "OT2_1Kings",
        "Name": "1 Kings 22",
        "XPath": "(/html[1]/body[@book='OT2_1Kings']//chapter)[22]",
        "Children": []
      }
    ]
  },
  {
    "IsVisible": true,
    "Book": "OT2_2Kings",
    "Name": "2 Kings",
    "XPath": "/html[1]/body[@book='OT2_2Kings']/book",
    "Children": [
      {
        "IsVisible": true,
        "Book": "OT2_2Kings",
        "Name": "2 Kings 1",
        "XPath": "(/html[1]/body[@book='OT2_2Kings']//chapter)[1]",
        "Children": []
      },
      {
        "IsVisible": true,
        "Book": "OT2_2Kings",
        "Name": "2 Kings 2",
        "XPath": "(/html[1]/body[@book='OT2_2Kings']//chapter)[2]",
        "Children": []
      },
      {
        "IsVisible": true,
        "Book": "OT2_2Kings",
        "Name": "2 Kings 3",
        "XPath": "(/html[1]/body[@book='OT2_2Kings']//chapter)[3]",
        "Children": []
      },
      {
        "IsVisible": true,
        "Book": "OT2_2Kings",
        "Name": "2 Kings 4",
        "XPath": "(/html[1]/body[@book='OT2_2Kings']//chapter)[4]",
        "Children": []
      },
      {
        "IsVisible": true,
        "Book": "OT2_2Kings",
        "Name": "2 Kings 5",
        "XPath": "(/html[1]/body[@book='OT2_2Kings']//chapter)[5]",
        "Children": []
      },
      {
        "IsVisible": true,
        "Book": "OT2_2Kings",
        "Name": "2 Kings 6",
        "XPath": "(/html[1]/body[@book='OT2_2Kings']//chapter)[6]",
        "Children": []
      },
      {
        "IsVisible": true,
        "Book": "OT2_2Kings",
        "Name": "2 Kings 7",
        "XPath": "(/html[1]/body[@book='OT2_2Kings']//chapter)[7]",
        "Children": []
      },
      {
        "IsVisible": true,
        "Book": "OT2_2Kings",
        "Name": "2 Kings 8",
        "XPath": "(/html[1]/body[@book='OT2_2Kings']//chapter)[8]",
        "Children": []
      },
      {
        "IsVisible": true,
        "Book": "OT2_2Kings",
        "Name": "2 Kings 9",
        "XPath": "(/html[1]/body[@book='OT2_2Kings']//chapter)[9]",
        "Children": []
      },
      {
        "IsVisible": true,
        "Book": "OT2_2Kings",
        "Name": "2 Kings 10",
        "XPath": "(/html[1]/body[@book='OT2_2Kings']//chapter)[10]",
        "Children": []
      },
      {
        "IsVisible": true,
        "Book": "OT2_2Kings",
        "Name": "2 Kings 11",
        "XPath": "(/html[1]/body[@book='OT2_2Kings']//chapter)[11]",
        "Children": []
      },
      {
        "IsVisible": true,
        "Book": "OT2_2Kings",
        "Name": "2 Kings 12",
        "XPath": "(/html[1]/body[@book='OT2_2Kings']//chapter)[12]",
        "Children": []
      },
      {
        "IsVisible": true,
        "Book": "OT2_2Kings",
        "Name": "2 Kings 13",
        "XPath": "(/html[1]/body[@book='OT2_2Kings']//chapter)[13]",
        "Children": []
      },
      {
        "IsVisible": true,
        "Book": "OT2_2Kings",
        "Name": "2 Kings 14",
        "XPath": "(/html[1]/body[@book='OT2_2Kings']//chapter)[14]",
        "Children": []
      },
      {
        "IsVisible": true,
        "Book": "OT2_2Kings",
        "Name": "2 Kings 15",
        "XPath": "(/html[1]/body[@book='OT2_2Kings']//chapter)[15]",
        "Children": []
      },
      {
        "IsVisible": true,
        "Book": "OT2_2Kings",
        "Name": "2 Kings 16",
        "XPath": "(/html[1]/body[@book='OT2_2Kings']//chapter)[16]",
        "Children": []
      },
      {
        "IsVisible": true,
        "Book": "OT2_2Kings",
        "Name": "2 Kings 17",
        "XPath": "(/html[1]/body[@book='OT2_2Kings']//chapter)[17]",
        "Children": []
      },
      {
        "IsVisible": true,
        "Book": "OT2_2Kings",
        "Name": "2 Kings 18",
        "XPath": "(/html[1]/body[@book='OT2_2Kings']//chapter)[18]",
        "Children": []
      },
      {
        "IsVisible": true,
        "Book": "OT2_2Kings",
        "Name": "2 Kings 19",
        "XPath": "(/html[1]/body[@book='OT2_2Kings']//chapter)[19]",
        "Children": []
      },
      {
        "IsVisible": true,
        "Book": "OT2_2Kings",
        "Name": "2 Kings 20",
        "XPath": "(/html[1]/body[@book='OT2_2Kings']//chapter)[20]",
        "Children": []
      },
      {
        "IsVisible": true,
        "Book": "OT2_2Kings",
        "Name": "2 Kings 21",
        "XPath": "(/html[1]/body[@book='OT2_2Kings']//chapter)[21]",
        "Children": []
      },
      {
        "IsVisible": true,
        "Book": "OT2_2Kings",
        "Name": "2 Kings 22",
        "XPath": "(/html[1]/body[@book='OT2_2Kings']//chapter)[22]",
        "Children": []
      },
      {
        "IsVisible": true,
        "Book": "OT2_2Kings",
        "Name": "2 Kings 23",
        "XPath": "(/html[1]/body[@book='OT2_2Kings']//chapter)[23]",
        "Children": []
      },
      {
        "IsVisible": true,
        "Book": "OT2_2Kings",
        "Name": "2 Kings 24",
        "XPath": "(/html[1]/body[@book='OT2_2Kings']//chapter)[24]",
        "Children": []
      },
      {
        "IsVisible": true,
        "Book": "OT2_2Kings",
        "Name": "2 Kings 25",
        "XPath": "(/html[1]/body[@book='OT2_2Kings']//chapter)[25]",
        "Children": []
      }
    ]
  },
  {
    "IsVisible": true,
    "Book": "OT2_1Chronicles",
    "Name": "1 Chronicles",
    "XPath": "/html[1]/body[@book='OT2_1Chronicles']/book",
    "Children": [
      {
        "IsVisible": true,
        "Book": "OT2_1Chronicles",
        "Name": "1 Chronicles 1",
        "XPath": "(/html[1]/body[@book='OT2_1Chronicles']//chapter)[1]",
        "Children": []
      },
      {
        "IsVisible": true,
        "Book": "OT2_1Chronicles",
        "Name": "1 Chronicles 2",
        "XPath": "(/html[1]/body[@book='OT2_1Chronicles']//chapter)[2]",
        "Children": []
      },
      {
        "IsVisible": true,
        "Book": "OT2_1Chronicles",
        "Name": "1 Chronicles 3",
        "XPath": "(/html[1]/body[@book='OT2_1Chronicles']//chapter)[3]",
        "Children": []
      },
      {
        "IsVisible": true,
        "Book": "OT2_1Chronicles",
        "Name": "1 Chronicles 4",
        "XPath": "(/html[1]/body[@book='OT2_1Chronicles']//chapter)[4]",
        "Children": []
      },
      {
        "IsVisible": true,
        "Book": "OT2_1Chronicles",
        "Name": "1 Chronicles 5",
        "XPath": "(/html[1]/body[@book='OT2_1Chronicles']//chapter)[5]",
        "Children": []
      },
      {
        "IsVisible": true,
        "Book": "OT2_1Chronicles",
        "Name": "1 Chronicles 6",
        "XPath": "(/html[1]/body[@book='OT2_1Chronicles']//chapter)[6]",
        "Children": []
      },
      {
        "IsVisible": true,
        "Book": "OT2_1Chronicles",
        "Name": "1 Chronicles 7",
        "XPath": "(/html[1]/body[@book='OT2_1Chronicles']//chapter)[7]",
        "Children": []
      },
      {
        "IsVisible": true,
        "Book": "OT2_1Chronicles",
        "Name": "1 Chronicles 8",
        "XPath": "(/html[1]/body[@book='OT2_1Chronicles']//chapter)[8]",
        "Children": []
      },
      {
        "IsVisible": true,
        "Book": "OT2_1Chronicles",
        "Name": "1 Chronicles 9",
        "XPath": "(/html[1]/body[@book='OT2_1Chronicles']//chapter)[9]",
        "Children": []
      },
      {
        "IsVisible": true,
        "Book": "OT2_1Chronicles",
        "Name": "1 Chronicles 10",
        "XPath": "(/html[1]/body[@book='OT2_1Chronicles']//chapter)[10]",
        "Children": []
      },
      {
        "IsVisible": true,
        "Book": "OT2_1Chronicles",
        "Name": "1 Chronicles 11",
        "XPath": "(/html[1]/body[@book='OT2_1Chronicles']//chapter)[11]",
        "Children": []
      },
      {
        "IsVisible": true,
        "Book": "OT2_1Chronicles",
        "Name": "1 Chronicles 12",
        "XPath": "(/html[1]/body[@book='OT2_1Chronicles']//chapter)[12]",
        "Children": []
      },
      {
        "IsVisible": true,
        "Book": "OT2_1Chronicles",
        "Name": "1 Chronicles 13",
        "XPath": "(/html[1]/body[@book='OT2_1Chronicles']//chapter)[13]",
        "Children": []
      },
      {
        "IsVisible": true,
        "Book": "OT2_1Chronicles",
        "Name": "1 Chronicles 14",
        "XPath": "(/html[1]/body[@book='OT2_1Chronicles']//chapter)[14]",
        "Children": []
      },
      {
        "IsVisible": true,
        "Book": "OT2_1Chronicles",
        "Name": "1 Chronicles 15",
        "XPath": "(/html[1]/body[@book='OT2_1Chronicles']//chapter)[15]",
        "Children": []
      },
      {
        "IsVisible": true,
        "Book": "OT2_1Chronicles",
        "Name": "1 Chronicles 16",
        "XPath": "(/html[1]/body[@book='OT2_1Chronicles']//chapter)[16]",
        "Children": []
      },
      {
        "IsVisible": true,
        "Book": "OT2_1Chronicles",
        "Name": "1 Chronicles 17",
        "XPath": "(/html[1]/body[@book='OT2_1Chronicles']//chapter)[17]",
        "Children": []
      },
      {
        "IsVisible": true,
        "Book": "OT2_1Chronicles",
        "Name": "1 Chronicles 18",
        "XPath": "(/html[1]/body[@book='OT2_1Chronicles']//chapter)[18]",
        "Children": []
      },
      {
        "IsVisible": true,
        "Book": "OT2_1Chronicles",
        "Name": "1 Chronicles 19",
        "XPath": "(/html[1]/body[@book='OT2_1Chronicles']//chapter)[19]",
        "Children": []
      },
      {
        "IsVisible": true,
        "Book": "OT2_1Chronicles",
        "Name": "1 Chronicles 20",
        "XPath": "(/html[1]/body[@book='OT2_1Chronicles']//chapter)[20]",
        "Children": []
      },
      {
        "IsVisible": true,
        "Book": "OT2_1Chronicles",
        "Name": "1 Chronicles 21",
        "XPath": "(/html[1]/body[@book='OT2_1Chronicles']//chapter)[21]",
        "Children": []
      },
      {
        "IsVisible": true,
        "Book": "OT2_1Chronicles",
        "Name": "1 Chronicles 22",
        "XPath": "(/html[1]/body[@book='OT2_1Chronicles']//chapter)[22]",
        "Children": []
      },
      {
        "IsVisible": true,
        "Book": "OT2_1Chronicles",
        "Name": "1 Chronicles 23",
        "XPath": "(/html[1]/body[@book='OT2_1Chronicles']//chapter)[23]",
        "Children": []
      },
      {
        "IsVisible": true,
        "Book": "OT2_1Chronicles",
        "Name": "1 Chronicles 24",
        "XPath": "(/html[1]/body[@book='OT2_1Chronicles']//chapter)[24]",
        "Children": []
      },
      {
        "IsVisible": true,
        "Book": "OT2_1Chronicles",
        "Name": "1 Chronicles 25",
        "XPath": "(/html[1]/body[@book='OT2_1Chronicles']//chapter)[25]",
        "Children": []
      },
      {
        "IsVisible": true,
        "Book": "OT2_1Chronicles",
        "Name": "1 Chronicles 26",
        "XPath": "(/html[1]/body[@book='OT2_1Chronicles']//chapter)[26]",
        "Children": []
      },
      {
        "IsVisible": true,
        "Book": "OT2_1Chronicles",
        "Name": "1 Chronicles 27",
        "XPath": "(/html[1]/body[@book='OT2_1Chronicles']//chapter)[27]",
        "Children": []
      },
      {
        "IsVisible": true,
        "Book": "OT2_1Chronicles",
        "Name": "1 Chronicles 28",
        "XPath": "(/html[1]/body[@book='OT2_1Chronicles']//chapter)[28]",
        "Children": []
      },
      {
        "IsVisible": true,
        "Book": "OT2_1Chronicles",
        "Name": "1 Chronicles 29",
        "XPath": "(/html[1]/body[@book='OT2_1Chronicles']//chapter)[29]",
        "Children": []
      }
    ]
  },
  {
    "IsVisible": true,
    "Book": "OT2_2Chronicles",
    "Name": "2 Chronicles",
    "XPath": "/html[1]/body[@book='OT2_2Chronicles']/book",
    "Children": [
      {
        "IsVisible": true,
        "Book": "OT2_2Chronicles",
        "Name": "2 Chronicles 1",
        "XPath": "(/html[1]/body[@book='OT2_2Chronicles']//chapter)[1]",
        "Children": []
      },
      {
        "IsVisible": true,
        "Book": "OT2_2Chronicles",
        "Name": "2 Chronicles 2",
        "XPath": "(/html[1]/body[@book='OT2_2Chronicles']//chapter)[2]",
        "Children": []
      },
      {
        "IsVisible": true,
        "Book": "OT2_2Chronicles",
        "Name": "2 Chronicles 3",
        "XPath": "(/html[1]/body[@book='OT2_2Chronicles']//chapter)[3]",
        "Children": []
      },
      {
        "IsVisible": true,
        "Book": "OT2_2Chronicles",
        "Name": "2 Chronicles 4",
        "XPath": "(/html[1]/body[@book='OT2_2Chronicles']//chapter)[4]",
        "Children": []
      },
      {
        "IsVisible": true,
        "Book": "OT2_2Chronicles",
        "Name": "2 Chronicles 5",
        "XPath": "(/html[1]/body[@book='OT2_2Chronicles']//chapter)[5]",
        "Children": []
      },
      {
        "IsVisible": true,
        "Book": "OT2_2Chronicles",
        "Name": "2 Chronicles 6",
        "XPath": "(/html[1]/body[@book='OT2_2Chronicles']//chapter)[6]",
        "Children": []
      },
      {
        "IsVisible": true,
        "Book": "OT2_2Chronicles",
        "Name": "2 Chronicles 7",
        "XPath": "(/html[1]/body[@book='OT2_2Chronicles']//chapter)[7]",
        "Children": []
      },
      {
        "IsVisible": true,
        "Book": "OT2_2Chronicles",
        "Name": "2 Chronicles 8",
        "XPath": "(/html[1]/body[@book='OT2_2Chronicles']//chapter)[8]",
        "Children": []
      },
      {
        "IsVisible": true,
        "Book": "OT2_2Chronicles",
        "Name": "2 Chronicles 9",
        "XPath": "(/html[1]/body[@book='OT2_2Chronicles']//chapter)[9]",
        "Children": []
      },
      {
        "IsVisible": true,
        "Book": "OT2_2Chronicles",
        "Name": "2 Chronicles 10",
        "XPath": "(/html[1]/body[@book='OT2_2Chronicles']//chapter)[10]",
        "Children": []
      },
      {
        "IsVisible": true,
        "Book": "OT2_2Chronicles",
        "Name": "2 Chronicles 11",
        "XPath": "(/html[1]/body[@book='OT2_2Chronicles']//chapter)[11]",
        "Children": []
      },
      {
        "IsVisible": true,
        "Book": "OT2_2Chronicles",
        "Name": "2 Chronicles 12",
        "XPath": "(/html[1]/body[@book='OT2_2Chronicles']//chapter)[12]",
        "Children": []
      },
      {
        "IsVisible": true,
        "Book": "OT2_2Chronicles",
        "Name": "2 Chronicles 13",
        "XPath": "(/html[1]/body[@book='OT2_2Chronicles']//chapter)[13]",
        "Children": []
      },
      {
        "IsVisible": true,
        "Book": "OT2_2Chronicles",
        "Name": "2 Chronicles 14",
        "XPath": "(/html[1]/body[@book='OT2_2Chronicles']//chapter)[14]",
        "Children": []
      },
      {
        "IsVisible": true,
        "Book": "OT2_2Chronicles",
        "Name": "2 Chronicles 15",
        "XPath": "(/html[1]/body[@book='OT2_2Chronicles']//chapter)[15]",
        "Children": []
      },
      {
        "IsVisible": true,
        "Book": "OT2_2Chronicles",
        "Name": "2 Chronicles 16",
        "XPath": "(/html[1]/body[@book='OT2_2Chronicles']//chapter)[16]",
        "Children": []
      },
      {
        "IsVisible": true,
        "Book": "OT2_2Chronicles",
        "Name": "2 Chronicles 17",
        "XPath": "(/html[1]/body[@book='OT2_2Chronicles']//chapter)[17]",
        "Children": []
      },
      {
        "IsVisible": true,
        "Book": "OT2_2Chronicles",
        "Name": "2 Chronicles 18",
        "XPath": "(/html[1]/body[@book='OT2_2Chronicles']//chapter)[18]",
        "Children": []
      },
      {
        "IsVisible": true,
        "Book": "OT2_2Chronicles",
        "Name": "2 Chronicles 19",
        "XPath": "(/html[1]/body[@book='OT2_2Chronicles']//chapter)[19]",
        "Children": []
      },
      {
        "IsVisible": true,
        "Book": "OT2_2Chronicles",
        "Name": "2 Chronicles 20",
        "XPath": "(/html[1]/body[@book='OT2_2Chronicles']//chapter)[20]",
        "Children": []
      },
      {
        "IsVisible": true,
        "Book": "OT2_2Chronicles",
        "Name": "2 Chronicles 21",
        "XPath": "(/html[1]/body[@book='OT2_2Chronicles']//chapter)[21]",
        "Children": []
      },
      {
        "IsVisible": true,
        "Book": "OT2_2Chronicles",
        "Name": "2 Chronicles 22",
        "XPath": "(/html[1]/body[@book='OT2_2Chronicles']//chapter)[22]",
        "Children": []
      },
      {
        "IsVisible": true,
        "Book": "OT2_2Chronicles",
        "Name": "2 Chronicles 23",
        "XPath": "(/html[1]/body[@book='OT2_2Chronicles']//chapter)[23]",
        "Children": []
      },
      {
        "IsVisible": true,
        "Book": "OT2_2Chronicles",
        "Name": "2 Chronicles 24",
        "XPath": "(/html[1]/body[@book='OT2_2Chronicles']//chapter)[24]",
        "Children": []
      },
      {
        "IsVisible": true,
        "Book": "OT2_2Chronicles",
        "Name": "2 Chronicles 25",
        "XPath": "(/html[1]/body[@book='OT2_2Chronicles']//chapter)[25]",
        "Children": []
      },
      {
        "IsVisible": true,
        "Book": "OT2_2Chronicles",
        "Name": "2 Chronicles 26",
        "XPath": "(/html[1]/body[@book='OT2_2Chronicles']//chapter)[26]",
        "Children": []
      },
      {
        "IsVisible": true,
        "Book": "OT2_2Chronicles",
        "Name": "2 Chronicles 27",
        "XPath": "(/html[1]/body[@book='OT2_2Chronicles']//chapter)[27]",
        "Children": []
      },
      {
        "IsVisible": true,
        "Book": "OT2_2Chronicles",
        "Name": "2 Chronicles 28",
        "XPath": "(/html[1]/body[@book='OT2_2Chronicles']//chapter)[28]",
        "Children": []
      },
      {
        "IsVisible": true,
        "Book": "OT2_2Chronicles",
        "Name": "2 Chronicles 29",
        "XPath": "(/html[1]/body[@book='OT2_2Chronicles']//chapter)[29]",
        "Children": []
      },
      {
        "IsVisible": true,
        "Book": "OT2_2Chronicles",
        "Name": "2 Chronicles 30",
        "XPath": "(/html[1]/body[@book='OT2_2Chronicles']//chapter)[30]",
        "Children": []
      },
      {
        "IsVisible": true,
        "Book": "OT2_2Chronicles",
        "Name": "2 Chronicles 31",
        "XPath": "(/html[1]/body[@book='OT2_2Chronicles']//chapter)[31]",
        "Children": []
      },
      {
        "IsVisible": true,
        "Book": "OT2_2Chronicles",
        "Name": "2 Chronicles 32",
        "XPath": "(/html[1]/body[@book='OT2_2Chronicles']//chapter)[32]",
        "Children": []
      },
      {
        "IsVisible": true,
        "Book": "OT2_2Chronicles",
        "Name": "2 Chronicles 33",
        "XPath": "(/html[1]/body[@book='OT2_2Chronicles']//chapter)[33]",
        "Children": []
      },
      {
        "IsVisible": true,
        "Book": "OT2_2Chronicles",
        "Name": "2 Chronicles 34",
        "XPath": "(/html[1]/body[@book='OT2_2Chronicles']//chapter)[34]",
        "Children": []
      },
      {
        "IsVisible": true,
        "Book": "OT2_2Chronicles",
        "Name": "2 Chronicles 35",
        "XPath": "(/html[1]/body[@book='OT2_2Chronicles']//chapter)[35]",
        "Children": []
      },
      {
        "IsVisible": true,
        "Book": "OT2_2Chronicles",
        "Name": "2 Chronicles 36",
        "XPath": "(/html[1]/body[@book='OT2_2Chronicles']//chapter)[36]",
        "Children": []
      }
    ]
  },
  {
    "IsVisible": true,
    "Book": "OT2_Ezra",
    "Name": "Ezra",
    "XPath": "/html[1]/body[@book='OT2_Ezra']/book",
    "Children": [
      {
        "IsVisible": true,
        "Book": "OT2_Ezra",
        "Name": "Ezra 1",
        "XPath": "(/html[1]/body[@book='OT2_Ezra']//chapter)[1]",
        "Children": []
      },
      {
        "IsVisible": true,
        "Book": "OT2_Ezra",
        "Name": "Ezra 2",
        "XPath": "(/html[1]/body[@book='OT2_Ezra']//chapter)[2]",
        "Children": []
      },
      {
        "IsVisible": true,
        "Book": "OT2_Ezra",
        "Name": "Ezra 3",
        "XPath": "(/html[1]/body[@book='OT2_Ezra']//chapter)[3]",
        "Children": []
      },
      {
        "IsVisible": true,
        "Book": "OT2_Ezra",
        "Name": "Ezra 4",
        "XPath": "(/html[1]/body[@book='OT2_Ezra']//chapter)[4]",
        "Children": []
      },
      {
        "IsVisible": true,
        "Book": "OT2_Ezra",
        "Name": "Ezra 5",
        "XPath": "(/html[1]/body[@book='OT2_Ezra']//chapter)[5]",
        "Children": []
      },
      {
        "IsVisible": true,
        "Book": "OT2_Ezra",
        "Name": "Ezra 6",
        "XPath": "(/html[1]/body[@book='OT2_Ezra']//chapter)[6]",
        "Children": []
      },
      {
        "IsVisible": true,
        "Book": "OT2_Ezra",
        "Name": "Ezra 7",
        "XPath": "(/html[1]/body[@book='OT2_Ezra']//chapter)[7]",
        "Children": []
      },
      {
        "IsVisible": true,
        "Book": "OT2_Ezra",
        "Name": "Ezra 8",
        "XPath": "(/html[1]/body[@book='OT2_Ezra']//chapter)[8]",
        "Children": []
      },
      {
        "IsVisible": true,
        "Book": "OT2_Ezra",
        "Name": "Ezra 9",
        "XPath": "(/html[1]/body[@book='OT2_Ezra']//chapter)[9]",
        "Children": []
      },
      {
        "IsVisible": true,
        "Book": "OT2_Ezra",
        "Name": "Ezra 10",
        "XPath": "(/html[1]/body[@book='OT2_Ezra']//chapter)[10]",
        "Children": []
      }
    ]
  },
  {
    "IsVisible": true,
    "Book": "OT2_Nehemiah",
    "Name": "Nehemiah",
    "XPath": "/html[1]/body[@book='OT2_Nehemiah']/book",
    "Children": [
      {
        "IsVisible": true,
        "Book": "OT2_Nehemiah",
        "Name": "Nehemiah 1",
        "XPath": "(/html[1]/body[@book='OT2_Nehemiah']//chapter)[1]",
        "Children": []
      },
      {
        "IsVisible": true,
        "Book": "OT2_Nehemiah",
        "Name": "Nehemiah 2",
        "XPath": "(/html[1]/body[@book='OT2_Nehemiah']//chapter)[2]",
        "Children": []
      },
      {
        "IsVisible": true,
        "Book": "OT2_Nehemiah",
        "Name": "Nehemiah 3",
        "XPath": "(/html[1]/body[@book='OT2_Nehemiah']//chapter)[3]",
        "Children": []
      },
      {
        "IsVisible": true,
        "Book": "OT2_Nehemiah",
        "Name": "Nehemiah 4",
        "XPath": "(/html[1]/body[@book='OT2_Nehemiah']//chapter)[4]",
        "Children": []
      },
      {
        "IsVisible": true,
        "Book": "OT2_Nehemiah",
        "Name": "Nehemiah 5",
        "XPath": "(/html[1]/body[@book='OT2_Nehemiah']//chapter)[5]",
        "Children": []
      },
      {
        "IsVisible": true,
        "Book": "OT2_Nehemiah",
        "Name": "Nehemiah 6",
        "XPath": "(/html[1]/body[@book='OT2_Nehemiah']//chapter)[6]",
        "Children": []
      },
      {
        "IsVisible": true,
        "Book": "OT2_Nehemiah",
        "Name": "Nehemiah 7",
        "XPath": "(/html[1]/body[@book='OT2_Nehemiah']//chapter)[7]",
        "Children": []
      },
      {
        "IsVisible": true,
        "Book": "OT2_Nehemiah",
        "Name": "Nehemiah 8",
        "XPath": "(/html[1]/body[@book='OT2_Nehemiah']//chapter)[8]",
        "Children": []
      },
      {
        "IsVisible": true,
        "Book": "OT2_Nehemiah",
        "Name": "Nehemiah 9",
        "XPath": "(/html[1]/body[@book='OT2_Nehemiah']//chapter)[9]",
        "Children": []
      },
      {
        "IsVisible": true,
        "Book": "OT2_Nehemiah",
        "Name": "Nehemiah 10",
        "XPath": "(/html[1]/body[@book='OT2_Nehemiah']//chapter)[10]",
        "Children": []
      },
      {
        "IsVisible": true,
        "Book": "OT2_Nehemiah",
        "Name": "Nehemiah 11",
        "XPath": "(/html[1]/body[@book='OT2_Nehemiah']//chapter)[11]",
        "Children": []
      },
      {
        "IsVisible": true,
        "Book": "OT2_Nehemiah",
        "Name": "Nehemiah 12",
        "XPath": "(/html[1]/body[@book='OT2_Nehemiah']//chapter)[12]",
        "Children": []
      },
      {
        "IsVisible": true,
        "Book": "OT2_Nehemiah",
        "Name": "Nehemiah 13",
        "XPath": "(/html[1]/body[@book='OT2_Nehemiah']//chapter)[13]",
        "Children": []
      }
    ]
  },
  {
    "IsVisible": true,
    "Book": "OT2_Esther",
    "Name": "Esther",
    "XPath": "/html[1]/body[@book='OT2_Esther']/book",
    "Children": [
      {
        "IsVisible": true,
        "Book": "OT2_Esther",
        "Name": "Esther 1",
        "XPath": "(/html[1]/body[@book='OT2_Esther']//chapter)[1]",
        "Children": []
      },
      {
        "IsVisible": true,
        "Book": "OT2_Esther",
        "Name": "Esther 2",
        "XPath": "(/html[1]/body[@book='OT2_Esther']//chapter)[2]",
        "Children": []
      },
      {
        "IsVisible": true,
        "Book": "OT2_Esther",
        "Name": "Esther 3",
        "XPath": "(/html[1]/body[@book='OT2_Esther']//chapter)[3]",
        "Children": []
      },
      {
        "IsVisible": true,
        "Book": "OT2_Esther",
        "Name": "Esther 4",
        "XPath": "(/html[1]/body[@book='OT2_Esther']//chapter)[4]",
        "Children": []
      },
      {
        "IsVisible": true,
        "Book": "OT2_Esther",
        "Name": "Esther 5",
        "XPath": "(/html[1]/body[@book='OT2_Esther']//chapter)[5]",
        "Children": []
      },
      {
        "IsVisible": true,
        "Book": "OT2_Esther",
        "Name": "Esther 6",
        "XPath": "(/html[1]/body[@book='OT2_Esther']//chapter)[6]",
        "Children": []
      },
      {
        "IsVisible": true,
        "Book": "OT2_Esther",
        "Name": "Esther 7",
        "XPath": "(/html[1]/body[@book='OT2_Esther']//chapter)[7]",
        "Children": []
      },
      {
        "IsVisible": true,
        "Book": "OT2_Esther",
        "Name": "Esther 8",
        "XPath": "(/html[1]/body[@book='OT2_Esther']//chapter)[8]",
        "Children": []
      },
      {
        "IsVisible": true,
        "Book": "OT2_Esther",
        "Name": "Esther 9",
        "XPath": "(/html[1]/body[@book='OT2_Esther']//chapter)[9]",
        "Children": []
      },
      {
        "IsVisible": true,
        "Book": "OT2_Esther",
        "Name": "Esther 10",
        "XPath": "(/html[1]/body[@book='OT2_Esther']//chapter)[10]",
        "Children": []
      }
    ]
  },
  {
    "IsVisible": true,
    "Book": "OT2_Job",
    "Name": "Job",
    "XPath": "/html[1]/body[@book='OT2_Job']/book",
    "Children": [
      {
        "IsVisible": true,
        "Book": "OT2_Job",
        "Name": "Job 1",
        "XPath": "(/html[1]/body[@book='OT2_Job']//chapter)[1]",
        "Children": []
      },
      {
        "IsVisible": true,
        "Book": "OT2_Job",
        "Name": "Job 2",
        "XPath": "(/html[1]/body[@book='OT2_Job']//chapter)[2]",
        "Children": []
      },
      {
        "IsVisible": true,
        "Book": "OT2_Job",
        "Name": "Job 3",
        "XPath": "(/html[1]/body[@book='OT2_Job']//chapter)[3]",
        "Children": []
      },
      {
        "IsVisible": true,
        "Book": "OT2_Job",
        "Name": "Job 4",
        "XPath": "(/html[1]/body[@book='OT2_Job']//chapter)[4]",
        "Children": []
      },
      {
        "IsVisible": true,
        "Book": "OT2_Job",
        "Name": "Job 5",
        "XPath": "(/html[1]/body[@book='OT2_Job']//chapter)[5]",
        "Children": []
      },
      {
        "IsVisible": true,
        "Book": "OT2_Job",
        "Name": "Job 6",
        "XPath": "(/html[1]/body[@book='OT2_Job']//chapter)[6]",
        "Children": []
      },
      {
        "IsVisible": true,
        "Book": "OT2_Job",
        "Name": "Job 7",
        "XPath": "(/html[1]/body[@book='OT2_Job']//chapter)[7]",
        "Children": []
      },
      {
        "IsVisible": true,
        "Book": "OT2_Job",
        "Name": "Job 8",
        "XPath": "(/html[1]/body[@book='OT2_Job']//chapter)[8]",
        "Children": []
      },
      {
        "IsVisible": true,
        "Book": "OT2_Job",
        "Name": "Job 9",
        "XPath": "(/html[1]/body[@book='OT2_Job']//chapter)[9]",
        "Children": []
      },
      {
        "IsVisible": true,
        "Book": "OT2_Job",
        "Name": "Job 10",
        "XPath": "(/html[1]/body[@book='OT2_Job']//chapter)[10]",
        "Children": []
      },
      {
        "IsVisible": true,
        "Book": "OT2_Job",
        "Name": "Job 11",
        "XPath": "(/html[1]/body[@book='OT2_Job']//chapter)[11]",
        "Children": []
      },
      {
        "IsVisible": true,
        "Book": "OT2_Job",
        "Name": "Job 12",
        "XPath": "(/html[1]/body[@book='OT2_Job']//chapter)[12]",
        "Children": []
      },
      {
        "IsVisible": true,
        "Book": "OT2_Job",
        "Name": "Job 13",
        "XPath": "(/html[1]/body[@book='OT2_Job']//chapter)[13]",
        "Children": []
      },
      {
        "IsVisible": true,
        "Book": "OT2_Job",
        "Name": "Job 14",
        "XPath": "(/html[1]/body[@book='OT2_Job']//chapter)[14]",
        "Children": []
      },
      {
        "IsVisible": true,
        "Book": "OT2_Job",
        "Name": "Job 15",
        "XPath": "(/html[1]/body[@book='OT2_Job']//chapter)[15]",
        "Children": []
      },
      {
        "IsVisible": true,
        "Book": "OT2_Job",
        "Name": "Job 16",
        "XPath": "(/html[1]/body[@book='OT2_Job']//chapter)[16]",
        "Children": []
      },
      {
        "IsVisible": true,
        "Book": "OT2_Job",
        "Name": "Job 17",
        "XPath": "(/html[1]/body[@book='OT2_Job']//chapter)[17]",
        "Children": []
      },
      {
        "IsVisible": true,
        "Book": "OT2_Job",
        "Name": "Job 18",
        "XPath": "(/html[1]/body[@book='OT2_Job']//chapter)[18]",
        "Children": []
      },
      {
        "IsVisible": true,
        "Book": "OT2_Job",
        "Name": "Job 19",
        "XPath": "(/html[1]/body[@book='OT2_Job']//chapter)[19]",
        "Children": []
      },
      {
        "IsVisible": true,
        "Book": "OT2_Job",
        "Name": "Job 20",
        "XPath": "(/html[1]/body[@book='OT2_Job']//chapter)[20]",
        "Children": []
      },
      {
        "IsVisible": true,
        "Book": "OT2_Job",
        "Name": "Job 21",
        "XPath": "(/html[1]/body[@book='OT2_Job']//chapter)[21]",
        "Children": []
      },
      {
        "IsVisible": true,
        "Book": "OT2_Job",
        "Name": "Job 22",
        "XPath": "(/html[1]/body[@book='OT2_Job']//chapter)[22]",
        "Children": []
      },
      {
        "IsVisible": true,
        "Book": "OT2_Job",
        "Name": "Job 23",
        "XPath": "(/html[1]/body[@book='OT2_Job']//chapter)[23]",
        "Children": []
      },
      {
        "IsVisible": true,
        "Book": "OT2_Job",
        "Name": "Job 24",
        "XPath": "(/html[1]/body[@book='OT2_Job']//chapter)[24]",
        "Children": []
      },
      {
        "IsVisible": true,
        "Book": "OT2_Job",
        "Name": "Job 25",
        "XPath": "(/html[1]/body[@book='OT2_Job']//chapter)[25]",
        "Children": []
      },
      {
        "IsVisible": true,
        "Book": "OT2_Job",
        "Name": "Job 26",
        "XPath": "(/html[1]/body[@book='OT2_Job']//chapter)[26]",
        "Children": []
      },
      {
        "IsVisible": true,
        "Book": "OT2_Job",
        "Name": "Job 27",
        "XPath": "(/html[1]/body[@book='OT2_Job']//chapter)[27]",
        "Children": []
      },
      {
        "IsVisible": true,
        "Book": "OT2_Job",
        "Name": "Job 28",
        "XPath": "(/html[1]/body[@book='OT2_Job']//chapter)[28]",
        "Children": []
      },
      {
        "IsVisible": true,
        "Book": "OT2_Job",
        "Name": "Job 29",
        "XPath": "(/html[1]/body[@book='OT2_Job']//chapter)[29]",
        "Children": []
      },
      {
        "IsVisible": true,
        "Book": "OT2_Job",
        "Name": "Job 30",
        "XPath": "(/html[1]/body[@book='OT2_Job']//chapter)[30]",
        "Children": []
      },
      {
        "IsVisible": true,
        "Book": "OT2_Job",
        "Name": "Job 31",
        "XPath": "(/html[1]/body[@book='OT2_Job']//chapter)[31]",
        "Children": []
      },
      {
        "IsVisible": true,
        "Book": "OT2_Job",
        "Name": "Job 32",
        "XPath": "(/html[1]/body[@book='OT2_Job']//chapter)[32]",
        "Children": []
      },
      {
        "IsVisible": true,
        "Book": "OT2_Job",
        "Name": "Job 33",
        "XPath": "(/html[1]/body[@book='OT2_Job']//chapter)[33]",
        "Children": []
      },
      {
        "IsVisible": true,
        "Book": "OT2_Job",
        "Name": "Job 34",
        "XPath": "(/html[1]/body[@book='OT2_Job']//chapter)[34]",
        "Children": []
      },
      {
        "IsVisible": true,
        "Book": "OT2_Job",
        "Name": "Job 35",
        "XPath": "(/html[1]/body[@book='OT2_Job']//chapter)[35]",
        "Children": []
      },
      {
        "IsVisible": true,
        "Book": "OT2_Job",
        "Name": "Job 36",
        "XPath": "(/html[1]/body[@book='OT2_Job']//chapter)[36]",
        "Children": []
      },
      {
        "IsVisible": true,
        "Book": "OT2_Job",
        "Name": "Job 37",
        "XPath": "(/html[1]/body[@book='OT2_Job']//chapter)[37]",
        "Children": []
      },
      {
        "IsVisible": true,
        "Book": "OT2_Job",
        "Name": "Job 38",
        "XPath": "(/html[1]/body[@book='OT2_Job']//chapter)[38]",
        "Children": []
      },
      {
        "IsVisible": true,
        "Book": "OT2_Job",
        "Name": "Job 39",
        "XPath": "(/html[1]/body[@book='OT2_Job']//chapter)[39]",
        "Children": []
      },
      {
        "IsVisible": true,
        "Book": "OT2_Job",
        "Name": "Job 40",
        "XPath": "(/html[1]/body[@book='OT2_Job']//chapter)[40]",
        "Children": []
      },
      {
        "IsVisible": true,
        "Book": "OT2_Job",
        "Name": "Job 41",
        "XPath": "(/html[1]/body[@book='OT2_Job']//chapter)[41]",
        "Children": []
      },
      {
        "IsVisible": true,
        "Book": "OT2_Job",
        "Name": "Job 42",
        "XPath": "(/html[1]/body[@book='OT2_Job']//chapter)[42]",
        "Children": []
      }
    ]
  },
  {
    "IsVisible": true,
    "Book": "OT2_Psalms",
    "Name": "Psalms",
    "XPath": "/html[1]/body[@book='OT2_Psalms']/book",
    "Children": [
      {
        "IsVisible": true,
        "Book": "OT2_Psalms",
        "Name": "Psalms 1",
        "XPath": "(/html[1]/body[@book='OT2_Psalms']//chapter)[1]",
        "Children": []
      },
      {
        "IsVisible": true,
        "Book": "OT2_Psalms",
        "Name": "Psalms 2",
        "XPath": "(/html[1]/body[@book='OT2_Psalms']//chapter)[2]",
        "Children": []
      },
      {
        "IsVisible": true,
        "Book": "OT2_Psalms",
        "Name": "Psalms 3",
        "XPath": "(/html[1]/body[@book='OT2_Psalms']//chapter)[3]",
        "Children": []
      },
      {
        "IsVisible": true,
        "Book": "OT2_Psalms",
        "Name": "Psalms 4",
        "XPath": "(/html[1]/body[@book='OT2_Psalms']//chapter)[4]",
        "Children": []
      },
      {
        "IsVisible": true,
        "Book": "OT2_Psalms",
        "Name": "Psalms 5",
        "XPath": "(/html[1]/body[@book='OT2_Psalms']//chapter)[5]",
        "Children": []
      },
      {
        "IsVisible": true,
        "Book": "OT2_Psalms",
        "Name": "Psalms 6",
        "XPath": "(/html[1]/body[@book='OT2_Psalms']//chapter)[6]",
        "Children": []
      },
      {
        "IsVisible": true,
        "Book": "OT2_Psalms",
        "Name": "Psalms 7",
        "XPath": "(/html[1]/body[@book='OT2_Psalms']//chapter)[7]",
        "Children": []
      },
      {
        "IsVisible": true,
        "Book": "OT2_Psalms",
        "Name": "Psalms 8",
        "XPath": "(/html[1]/body[@book='OT2_Psalms']//chapter)[8]",
        "Children": []
      },
      {
        "IsVisible": true,
        "Book": "OT2_Psalms",
        "Name": "Psalms 9",
        "XPath": "(/html[1]/body[@book='OT2_Psalms']//chapter)[9]",
        "Children": []
      },
      {
        "IsVisible": true,
        "Book": "OT2_Psalms",
        "Name": "Psalms 10",
        "XPath": "(/html[1]/body[@book='OT2_Psalms']//chapter)[10]",
        "Children": []
      },
      {
        "IsVisible": true,
        "Book": "OT2_Psalms",
        "Name": "Psalms 11",
        "XPath": "(/html[1]/body[@book='OT2_Psalms']//chapter)[11]",
        "Children": []
      },
      {
        "IsVisible": true,
        "Book": "OT2_Psalms",
        "Name": "Psalms 12",
        "XPath": "(/html[1]/body[@book='OT2_Psalms']//chapter)[12]",
        "Children": []
      },
      {
        "IsVisible": true,
        "Book": "OT2_Psalms",
        "Name": "Psalms 13",
        "XPath": "(/html[1]/body[@book='OT2_Psalms']//chapter)[13]",
        "Children": []
      },
      {
        "IsVisible": true,
        "Book": "OT2_Psalms",
        "Name": "Psalms 14",
        "XPath": "(/html[1]/body[@book='OT2_Psalms']//chapter)[14]",
        "Children": []
      },
      {
        "IsVisible": true,
        "Book": "OT2_Psalms",
        "Name": "Psalms 15",
        "XPath": "(/html[1]/body[@book='OT2_Psalms']//chapter)[15]",
        "Children": []
      },
      {
        "IsVisible": true,
        "Book": "OT2_Psalms",
        "Name": "Psalms 16",
        "XPath": "(/html[1]/body[@book='OT2_Psalms']//chapter)[16]",
        "Children": []
      },
      {
        "IsVisible": true,
        "Book": "OT2_Psalms",
        "Name": "Psalms 17",
        "XPath": "(/html[1]/body[@book='OT2_Psalms']//chapter)[17]",
        "Children": []
      },
      {
        "IsVisible": true,
        "Book": "OT2_Psalms",
        "Name": "Psalms 18",
        "XPath": "(/html[1]/body[@book='OT2_Psalms']//chapter)[18]",
        "Children": []
      },
      {
        "IsVisible": true,
        "Book": "OT2_Psalms",
        "Name": "Psalms 19",
        "XPath": "(/html[1]/body[@book='OT2_Psalms']//chapter)[19]",
        "Children": []
      },
      {
        "IsVisible": true,
        "Book": "OT2_Psalms",
        "Name": "Psalms 20",
        "XPath": "(/html[1]/body[@book='OT2_Psalms']//chapter)[20]",
        "Children": []
      },
      {
        "IsVisible": true,
        "Book": "OT2_Psalms",
        "Name": "Psalms 21",
        "XPath": "(/html[1]/body[@book='OT2_Psalms']//chapter)[21]",
        "Children": []
      },
      {
        "IsVisible": true,
        "Book": "OT2_Psalms",
        "Name": "Psalms 22",
        "XPath": "(/html[1]/body[@book='OT2_Psalms']//chapter)[22]",
        "Children": []
      },
      {
        "IsVisible": true,
        "Book": "OT2_Psalms",
        "Name": "Psalms 23",
        "XPath": "(/html[1]/body[@book='OT2_Psalms']//chapter)[23]",
        "Children": []
      },
      {
        "IsVisible": true,
        "Book": "OT2_Psalms",
        "Name": "Psalms 24",
        "XPath": "(/html[1]/body[@book='OT2_Psalms']//chapter)[24]",
        "Children": []
      },
      {
        "IsVisible": true,
        "Book": "OT2_Psalms",
        "Name": "Psalms 25",
        "XPath": "(/html[1]/body[@book='OT2_Psalms']//chapter)[25]",
        "Children": []
      },
      {
        "IsVisible": true,
        "Book": "OT2_Psalms",
        "Name": "Psalms 26",
        "XPath": "(/html[1]/body[@book='OT2_Psalms']//chapter)[26]",
        "Children": []
      },
      {
        "IsVisible": true,
        "Book": "OT2_Psalms",
        "Name": "Psalms 27",
        "XPath": "(/html[1]/body[@book='OT2_Psalms']//chapter)[27]",
        "Children": []
      },
      {
        "IsVisible": true,
        "Book": "OT2_Psalms",
        "Name": "Psalms 28",
        "XPath": "(/html[1]/body[@book='OT2_Psalms']//chapter)[28]",
        "Children": []
      },
      {
        "IsVisible": true,
        "Book": "OT2_Psalms",
        "Name": "Psalms 29",
        "XPath": "(/html[1]/body[@book='OT2_Psalms']//chapter)[29]",
        "Children": []
      },
      {
        "IsVisible": true,
        "Book": "OT2_Psalms",
        "Name": "Psalms 30",
        "XPath": "(/html[1]/body[@book='OT2_Psalms']//chapter)[30]",
        "Children": []
      },
      {
        "IsVisible": true,
        "Book": "OT2_Psalms",
        "Name": "Psalms 31",
        "XPath": "(/html[1]/body[@book='OT2_Psalms']//chapter)[31]",
        "Children": []
      },
      {
        "IsVisible": true,
        "Book": "OT2_Psalms",
        "Name": "Psalms 32",
        "XPath": "(/html[1]/body[@book='OT2_Psalms']//chapter)[32]",
        "Children": []
      },
      {
        "IsVisible": true,
        "Book": "OT2_Psalms",
        "Name": "Psalms 33",
        "XPath": "(/html[1]/body[@book='OT2_Psalms']//chapter)[33]",
        "Children": []
      },
      {
        "IsVisible": true,
        "Book": "OT2_Psalms",
        "Name": "Psalms 34",
        "XPath": "(/html[1]/body[@book='OT2_Psalms']//chapter)[34]",
        "Children": []
      },
      {
        "IsVisible": true,
        "Book": "OT2_Psalms",
        "Name": "Psalms 35",
        "XPath": "(/html[1]/body[@book='OT2_Psalms']//chapter)[35]",
        "Children": []
      },
      {
        "IsVisible": true,
        "Book": "OT2_Psalms",
        "Name": "Psalms 36",
        "XPath": "(/html[1]/body[@book='OT2_Psalms']//chapter)[36]",
        "Children": []
      },
      {
        "IsVisible": true,
        "Book": "OT2_Psalms",
        "Name": "Psalms 37",
        "XPath": "(/html[1]/body[@book='OT2_Psalms']//chapter)[37]",
        "Children": []
      },
      {
        "IsVisible": true,
        "Book": "OT2_Psalms",
        "Name": "Psalms 38",
        "XPath": "(/html[1]/body[@book='OT2_Psalms']//chapter)[38]",
        "Children": []
      },
      {
        "IsVisible": true,
        "Book": "OT2_Psalms",
        "Name": "Psalms 39",
        "XPath": "(/html[1]/body[@book='OT2_Psalms']//chapter)[39]",
        "Children": []
      },
      {
        "IsVisible": true,
        "Book": "OT2_Psalms",
        "Name": "Psalms 40",
        "XPath": "(/html[1]/body[@book='OT2_Psalms']//chapter)[40]",
        "Children": []
      },
      {
        "IsVisible": true,
        "Book": "OT2_Psalms",
        "Name": "Psalms 41",
        "XPath": "(/html[1]/body[@book='OT2_Psalms']//chapter)[41]",
        "Children": []
      },
      {
        "IsVisible": true,
        "Book": "OT2_Psalms",
        "Name": "Psalms 42",
        "XPath": "(/html[1]/body[@book='OT2_Psalms']//chapter)[42]",
        "Children": []
      },
      {
        "IsVisible": true,
        "Book": "OT2_Psalms",
        "Name": "Psalms 43",
        "XPath": "(/html[1]/body[@book='OT2_Psalms']//chapter)[43]",
        "Children": []
      },
      {
        "IsVisible": true,
        "Book": "OT2_Psalms",
        "Name": "Psalms 44",
        "XPath": "(/html[1]/body[@book='OT2_Psalms']//chapter)[44]",
        "Children": []
      },
      {
        "IsVisible": true,
        "Book": "OT2_Psalms",
        "Name": "Psalms 45",
        "XPath": "(/html[1]/body[@book='OT2_Psalms']//chapter)[45]",
        "Children": []
      },
      {
        "IsVisible": true,
        "Book": "OT2_Psalms",
        "Name": "Psalms 46",
        "XPath": "(/html[1]/body[@book='OT2_Psalms']//chapter)[46]",
        "Children": []
      },
      {
        "IsVisible": true,
        "Book": "OT2_Psalms",
        "Name": "Psalms 47",
        "XPath": "(/html[1]/body[@book='OT2_Psalms']//chapter)[47]",
        "Children": []
      },
      {
        "IsVisible": true,
        "Book": "OT2_Psalms",
        "Name": "Psalms 48",
        "XPath": "(/html[1]/body[@book='OT2_Psalms']//chapter)[48]",
        "Children": []
      },
      {
        "IsVisible": true,
        "Book": "OT2_Psalms",
        "Name": "Psalms 49",
        "XPath": "(/html[1]/body[@book='OT2_Psalms']//chapter)[49]",
        "Children": []
      },
      {
        "IsVisible": true,
        "Book": "OT2_Psalms",
        "Name": "Psalms 50",
        "XPath": "(/html[1]/body[@book='OT2_Psalms']//chapter)[50]",
        "Children": []
      },
      {
        "IsVisible": true,
        "Book": "OT2_Psalms",
        "Name": "Psalms 51",
        "XPath": "(/html[1]/body[@book='OT2_Psalms']//chapter)[51]",
        "Children": []
      },
      {
        "IsVisible": true,
        "Book": "OT2_Psalms",
        "Name": "Psalms 52",
        "XPath": "(/html[1]/body[@book='OT2_Psalms']//chapter)[52]",
        "Children": []
      },
      {
        "IsVisible": true,
        "Book": "OT2_Psalms",
        "Name": "Psalms 53",
        "XPath": "(/html[1]/body[@book='OT2_Psalms']//chapter)[53]",
        "Children": []
      },
      {
        "IsVisible": true,
        "Book": "OT2_Psalms",
        "Name": "Psalms 54",
        "XPath": "(/html[1]/body[@book='OT2_Psalms']//chapter)[54]",
        "Children": []
      },
      {
        "IsVisible": true,
        "Book": "OT2_Psalms",
        "Name": "Psalms 55",
        "XPath": "(/html[1]/body[@book='OT2_Psalms']//chapter)[55]",
        "Children": []
      },
      {
        "IsVisible": true,
        "Book": "OT2_Psalms",
        "Name": "Psalms 56",
        "XPath": "(/html[1]/body[@book='OT2_Psalms']//chapter)[56]",
        "Children": []
      },
      {
        "IsVisible": true,
        "Book": "OT2_Psalms",
        "Name": "Psalms 57",
        "XPath": "(/html[1]/body[@book='OT2_Psalms']//chapter)[57]",
        "Children": []
      },
      {
        "IsVisible": true,
        "Book": "OT2_Psalms",
        "Name": "Psalms 58",
        "XPath": "(/html[1]/body[@book='OT2_Psalms']//chapter)[58]",
        "Children": []
      },
      {
        "IsVisible": true,
        "Book": "OT2_Psalms",
        "Name": "Psalms 59",
        "XPath": "(/html[1]/body[@book='OT2_Psalms']//chapter)[59]",
        "Children": []
      },
      {
        "IsVisible": true,
        "Book": "OT2_Psalms",
        "Name": "Psalms 60",
        "XPath": "(/html[1]/body[@book='OT2_Psalms']//chapter)[60]",
        "Children": []
      },
      {
        "IsVisible": true,
        "Book": "OT2_Psalms",
        "Name": "Psalms 61",
        "XPath": "(/html[1]/body[@book='OT2_Psalms']//chapter)[61]",
        "Children": []
      },
      {
        "IsVisible": true,
        "Book": "OT2_Psalms",
        "Name": "Psalms 62",
        "XPath": "(/html[1]/body[@book='OT2_Psalms']//chapter)[62]",
        "Children": []
      },
      {
        "IsVisible": true,
        "Book": "OT2_Psalms",
        "Name": "Psalms 63",
        "XPath": "(/html[1]/body[@book='OT2_Psalms']//chapter)[63]",
        "Children": []
      },
      {
        "IsVisible": true,
        "Book": "OT2_Psalms",
        "Name": "Psalms 64",
        "XPath": "(/html[1]/body[@book='OT2_Psalms']//chapter)[64]",
        "Children": []
      },
      {
        "IsVisible": true,
        "Book": "OT2_Psalms",
        "Name": "Psalms 65",
        "XPath": "(/html[1]/body[@book='OT2_Psalms']//chapter)[65]",
        "Children": []
      },
      {
        "IsVisible": true,
        "Book": "OT2_Psalms",
        "Name": "Psalms 66",
        "XPath": "(/html[1]/body[@book='OT2_Psalms']//chapter)[66]",
        "Children": []
      },
      {
        "IsVisible": true,
        "Book": "OT2_Psalms",
        "Name": "Psalms 67",
        "XPath": "(/html[1]/body[@book='OT2_Psalms']//chapter)[67]",
        "Children": []
      },
      {
        "IsVisible": true,
        "Book": "OT2_Psalms",
        "Name": "Psalms 68",
        "XPath": "(/html[1]/body[@book='OT2_Psalms']//chapter)[68]",
        "Children": []
      },
      {
        "IsVisible": true,
        "Book": "OT2_Psalms",
        "Name": "Psalms 69",
        "XPath": "(/html[1]/body[@book='OT2_Psalms']//chapter)[69]",
        "Children": []
      },
      {
        "IsVisible": true,
        "Book": "OT2_Psalms",
        "Name": "Psalms 70",
        "XPath": "(/html[1]/body[@book='OT2_Psalms']//chapter)[70]",
        "Children": []
      },
      {
        "IsVisible": true,
        "Book": "OT2_Psalms",
        "Name": "Psalms 71",
        "XPath": "(/html[1]/body[@book='OT2_Psalms']//chapter)[71]",
        "Children": []
      },
      {
        "IsVisible": true,
        "Book": "OT2_Psalms",
        "Name": "Psalms 72",
        "XPath": "(/html[1]/body[@book='OT2_Psalms']//chapter)[72]",
        "Children": []
      },
      {
        "IsVisible": true,
        "Book": "OT2_Psalms",
        "Name": "Psalms 73",
        "XPath": "(/html[1]/body[@book='OT2_Psalms']//chapter)[73]",
        "Children": []
      },
      {
        "IsVisible": true,
        "Book": "OT2_Psalms",
        "Name": "Psalms 74",
        "XPath": "(/html[1]/body[@book='OT2_Psalms']//chapter)[74]",
        "Children": []
      },
      {
        "IsVisible": true,
        "Book": "OT2_Psalms",
        "Name": "Psalms 75",
        "XPath": "(/html[1]/body[@book='OT2_Psalms']//chapter)[75]",
        "Children": []
      },
      {
        "IsVisible": true,
        "Book": "OT2_Psalms",
        "Name": "Psalms 76",
        "XPath": "(/html[1]/body[@book='OT2_Psalms']//chapter)[76]",
        "Children": []
      },
      {
        "IsVisible": true,
        "Book": "OT2_Psalms",
        "Name": "Psalms 77",
        "XPath": "(/html[1]/body[@book='OT2_Psalms']//chapter)[77]",
        "Children": []
      },
      {
        "IsVisible": true,
        "Book": "OT2_Psalms",
        "Name": "Psalms 78",
        "XPath": "(/html[1]/body[@book='OT2_Psalms']//chapter)[78]",
        "Children": []
      },
      {
        "IsVisible": true,
        "Book": "OT2_Psalms",
        "Name": "Psalms 79",
        "XPath": "(/html[1]/body[@book='OT2_Psalms']//chapter)[79]",
        "Children": []
      },
      {
        "IsVisible": true,
        "Book": "OT2_Psalms",
        "Name": "Psalms 80",
        "XPath": "(/html[1]/body[@book='OT2_Psalms']//chapter)[80]",
        "Children": []
      },
      {
        "IsVisible": true,
        "Book": "OT2_Psalms",
        "Name": "Psalms 81",
        "XPath": "(/html[1]/body[@book='OT2_Psalms']//chapter)[81]",
        "Children": []
      },
      {
        "IsVisible": true,
        "Book": "OT2_Psalms",
        "Name": "Psalms 82",
        "XPath": "(/html[1]/body[@book='OT2_Psalms']//chapter)[82]",
        "Children": []
      },
      {
        "IsVisible": true,
        "Book": "OT2_Psalms",
        "Name": "Psalms 83",
        "XPath": "(/html[1]/body[@book='OT2_Psalms']//chapter)[83]",
        "Children": []
      },
      {
        "IsVisible": true,
        "Book": "OT2_Psalms",
        "Name": "Psalms 84",
        "XPath": "(/html[1]/body[@book='OT2_Psalms']//chapter)[84]",
        "Children": []
      },
      {
        "IsVisible": true,
        "Book": "OT2_Psalms",
        "Name": "Psalms 85",
        "XPath": "(/html[1]/body[@book='OT2_Psalms']//chapter)[85]",
        "Children": []
      },
      {
        "IsVisible": true,
        "Book": "OT2_Psalms",
        "Name": "Psalms 86",
        "XPath": "(/html[1]/body[@book='OT2_Psalms']//chapter)[86]",
        "Children": []
      },
      {
        "IsVisible": true,
        "Book": "OT2_Psalms",
        "Name": "Psalms 87",
        "XPath": "(/html[1]/body[@book='OT2_Psalms']//chapter)[87]",
        "Children": []
      },
      {
        "IsVisible": true,
        "Book": "OT2_Psalms",
        "Name": "Psalms 88",
        "XPath": "(/html[1]/body[@book='OT2_Psalms']//chapter)[88]",
        "Children": []
      },
      {
        "IsVisible": true,
        "Book": "OT2_Psalms",
        "Name": "Psalms 89",
        "XPath": "(/html[1]/body[@book='OT2_Psalms']//chapter)[89]",
        "Children": []
      },
      {
        "IsVisible": true,
        "Book": "OT2_Psalms",
        "Name": "Psalms 90",
        "XPath": "(/html[1]/body[@book='OT2_Psalms']//chapter)[90]",
        "Children": []
      },
      {
        "IsVisible": true,
        "Book": "OT2_Psalms",
        "Name": "Psalms 91",
        "XPath": "(/html[1]/body[@book='OT2_Psalms']//chapter)[91]",
        "Children": []
      },
      {
        "IsVisible": true,
        "Book": "OT2_Psalms",
        "Name": "Psalms 92",
        "XPath": "(/html[1]/body[@book='OT2_Psalms']//chapter)[92]",
        "Children": []
      },
      {
        "IsVisible": true,
        "Book": "OT2_Psalms",
        "Name": "Psalms 93",
        "XPath": "(/html[1]/body[@book='OT2_Psalms']//chapter)[93]",
        "Children": []
      },
      {
        "IsVisible": true,
        "Book": "OT2_Psalms",
        "Name": "Psalms 94",
        "XPath": "(/html[1]/body[@book='OT2_Psalms']//chapter)[94]",
        "Children": []
      },
      {
        "IsVisible": true,
        "Book": "OT2_Psalms",
        "Name": "Psalms 95",
        "XPath": "(/html[1]/body[@book='OT2_Psalms']//chapter)[95]",
        "Children": []
      },
      {
        "IsVisible": true,
        "Book": "OT2_Psalms",
        "Name": "Psalms 96",
        "XPath": "(/html[1]/body[@book='OT2_Psalms']//chapter)[96]",
        "Children": []
      },
      {
        "IsVisible": true,
        "Book": "OT2_Psalms",
        "Name": "Psalms 97",
        "XPath": "(/html[1]/body[@book='OT2_Psalms']//chapter)[97]",
        "Children": []
      },
      {
        "IsVisible": true,
        "Book": "OT2_Psalms",
        "Name": "Psalms 98",
        "XPath": "(/html[1]/body[@book='OT2_Psalms']//chapter)[98]",
        "Children": []
      },
      {
        "IsVisible": true,
        "Book": "OT2_Psalms",
        "Name": "Psalms 99",
        "XPath": "(/html[1]/body[@book='OT2_Psalms']//chapter)[99]",
        "Children": []
      },
      {
        "IsVisible": true,
        "Book": "OT2_Psalms",
        "Name": "Psalms 100",
        "XPath": "(/html[1]/body[@book='OT2_Psalms']//chapter)[100]",
        "Children": []
      },
      {
        "IsVisible": true,
        "Book": "OT2_Psalms",
        "Name": "Psalms 101",
        "XPath": "(/html[1]/body[@book='OT2_Psalms']//chapter)[101]",
        "Children": []
      },
      {
        "IsVisible": true,
        "Book": "OT2_Psalms",
        "Name": "Psalms 102",
        "XPath": "(/html[1]/body[@book='OT2_Psalms']//chapter)[102]",
        "Children": []
      },
      {
        "IsVisible": true,
        "Book": "OT2_Psalms",
        "Name": "Psalms 103",
        "XPath": "(/html[1]/body[@book='OT2_Psalms']//chapter)[103]",
        "Children": []
      },
      {
        "IsVisible": true,
        "Book": "OT2_Psalms",
        "Name": "Psalms 104",
        "XPath": "(/html[1]/body[@book='OT2_Psalms']//chapter)[104]",
        "Children": []
      },
      {
        "IsVisible": true,
        "Book": "OT2_Psalms",
        "Name": "Psalms 105",
        "XPath": "(/html[1]/body[@book='OT2_Psalms']//chapter)[105]",
        "Children": []
      },
      {
        "IsVisible": true,
        "Book": "OT2_Psalms",
        "Name": "Psalms 106",
        "XPath": "(/html[1]/body[@book='OT2_Psalms']//chapter)[106]",
        "Children": []
      },
      {
        "IsVisible": true,
        "Book": "OT2_Psalms",
        "Name": "Psalms 107",
        "XPath": "(/html[1]/body[@book='OT2_Psalms']//chapter)[107]",
        "Children": []
      },
      {
        "IsVisible": true,
        "Book": "OT2_Psalms",
        "Name": "Psalms 108",
        "XPath": "(/html[1]/body[@book='OT2_Psalms']//chapter)[108]",
        "Children": []
      },
      {
        "IsVisible": true,
        "Book": "OT2_Psalms",
        "Name": "Psalms 109",
        "XPath": "(/html[1]/body[@book='OT2_Psalms']//chapter)[109]",
        "Children": []
      },
      {
        "IsVisible": true,
        "Book": "OT2_Psalms",
        "Name": "Psalms 110",
        "XPath": "(/html[1]/body[@book='OT2_Psalms']//chapter)[110]",
        "Children": []
      },
      {
        "IsVisible": true,
        "Book": "OT2_Psalms",
        "Name": "Psalms 111",
        "XPath": "(/html[1]/body[@book='OT2_Psalms']//chapter)[111]",
        "Children": []
      },
      {
        "IsVisible": true,
        "Book": "OT2_Psalms",
        "Name": "Psalms 112",
        "XPath": "(/html[1]/body[@book='OT2_Psalms']//chapter)[112]",
        "Children": []
      },
      {
        "IsVisible": true,
        "Book": "OT2_Psalms",
        "Name": "Psalms 113",
        "XPath": "(/html[1]/body[@book='OT2_Psalms']//chapter)[113]",
        "Children": []
      },
      {
        "IsVisible": true,
        "Book": "OT2_Psalms",
        "Name": "Psalms 114",
        "XPath": "(/html[1]/body[@book='OT2_Psalms']//chapter)[114]",
        "Children": []
      },
      {
        "IsVisible": true,
        "Book": "OT2_Psalms",
        "Name": "Psalms 115",
        "XPath": "(/html[1]/body[@book='OT2_Psalms']//chapter)[115]",
        "Children": []
      },
      {
        "IsVisible": true,
        "Book": "OT2_Psalms",
        "Name": "Psalms 116",
        "XPath": "(/html[1]/body[@book='OT2_Psalms']//chapter)[116]",
        "Children": []
      },
      {
        "IsVisible": true,
        "Book": "OT2_Psalms",
        "Name": "Psalms 117",
        "XPath": "(/html[1]/body[@book='OT2_Psalms']//chapter)[117]",
        "Children": []
      },
      {
        "IsVisible": true,
        "Book": "OT2_Psalms",
        "Name": "Psalms 118",
        "XPath": "(/html[1]/body[@book='OT2_Psalms']//chapter)[118]",
        "Children": []
      },
      {
        "IsVisible": true,
        "Book": "OT2_Psalms",
        "Name": "Psalms 119",
        "XPath": "(/html[1]/body[@book='OT2_Psalms']//chapter)[119]",
        "Children": []
      },
      {
        "IsVisible": true,
        "Book": "OT2_Psalms",
        "Name": "Psalms 120",
        "XPath": "(/html[1]/body[@book='OT2_Psalms']//chapter)[120]",
        "Children": []
      },
      {
        "IsVisible": true,
        "Book": "OT2_Psalms",
        "Name": "Psalms 121",
        "XPath": "(/html[1]/body[@book='OT2_Psalms']//chapter)[121]",
        "Children": []
      },
      {
        "IsVisible": true,
        "Book": "OT2_Psalms",
        "Name": "Psalms 122",
        "XPath": "(/html[1]/body[@book='OT2_Psalms']//chapter)[122]",
        "Children": []
      },
      {
        "IsVisible": true,
        "Book": "OT2_Psalms",
        "Name": "Psalms 123",
        "XPath": "(/html[1]/body[@book='OT2_Psalms']//chapter)[123]",
        "Children": []
      },
      {
        "IsVisible": true,
        "Book": "OT2_Psalms",
        "Name": "Psalms 124",
        "XPath": "(/html[1]/body[@book='OT2_Psalms']//chapter)[124]",
        "Children": []
      },
      {
        "IsVisible": true,
        "Book": "OT2_Psalms",
        "Name": "Psalms 125",
        "XPath": "(/html[1]/body[@book='OT2_Psalms']//chapter)[125]",
        "Children": []
      },
      {
        "IsVisible": true,
        "Book": "OT2_Psalms",
        "Name": "Psalms 126",
        "XPath": "(/html[1]/body[@book='OT2_Psalms']//chapter)[126]",
        "Children": []
      },
      {
        "IsVisible": true,
        "Book": "OT2_Psalms",
        "Name": "Psalms 127",
        "XPath": "(/html[1]/body[@book='OT2_Psalms']//chapter)[127]",
        "Children": []
      },
      {
        "IsVisible": true,
        "Book": "OT2_Psalms",
        "Name": "Psalms 128",
        "XPath": "(/html[1]/body[@book='OT2_Psalms']//chapter)[128]",
        "Children": []
      },
      {
        "IsVisible": true,
        "Book": "OT2_Psalms",
        "Name": "Psalms 129",
        "XPath": "(/html[1]/body[@book='OT2_Psalms']//chapter)[129]",
        "Children": []
      },
      {
        "IsVisible": true,
        "Book": "OT2_Psalms",
        "Name": "Psalms 130",
        "XPath": "(/html[1]/body[@book='OT2_Psalms']//chapter)[130]",
        "Children": []
      },
      {
        "IsVisible": true,
        "Book": "OT2_Psalms",
        "Name": "Psalms 131",
        "XPath": "(/html[1]/body[@book='OT2_Psalms']//chapter)[131]",
        "Children": []
      },
      {
        "IsVisible": true,
        "Book": "OT2_Psalms",
        "Name": "Psalms 132",
        "XPath": "(/html[1]/body[@book='OT2_Psalms']//chapter)[132]",
        "Children": []
      },
      {
        "IsVisible": true,
        "Book": "OT2_Psalms",
        "Name": "Psalms 133",
        "XPath": "(/html[1]/body[@book='OT2_Psalms']//chapter)[133]",
        "Children": []
      },
      {
        "IsVisible": true,
        "Book": "OT2_Psalms",
        "Name": "Psalms 134",
        "XPath": "(/html[1]/body[@book='OT2_Psalms']//chapter)[134]",
        "Children": []
      },
      {
        "IsVisible": true,
        "Book": "OT2_Psalms",
        "Name": "Psalms 135",
        "XPath": "(/html[1]/body[@book='OT2_Psalms']//chapter)[135]",
        "Children": []
      },
      {
        "IsVisible": true,
        "Book": "OT2_Psalms",
        "Name": "Psalms 136",
        "XPath": "(/html[1]/body[@book='OT2_Psalms']//chapter)[136]",
        "Children": []
      },
      {
        "IsVisible": true,
        "Book": "OT2_Psalms",
        "Name": "Psalms 137",
        "XPath": "(/html[1]/body[@book='OT2_Psalms']//chapter)[137]",
        "Children": []
      },
      {
        "IsVisible": true,
        "Book": "OT2_Psalms",
        "Name": "Psalms 138",
        "XPath": "(/html[1]/body[@book='OT2_Psalms']//chapter)[138]",
        "Children": []
      },
      {
        "IsVisible": true,
        "Book": "OT2_Psalms",
        "Name": "Psalms 139",
        "XPath": "(/html[1]/body[@book='OT2_Psalms']//chapter)[139]",
        "Children": []
      },
      {
        "IsVisible": true,
        "Book": "OT2_Psalms",
        "Name": "Psalms 140",
        "XPath": "(/html[1]/body[@book='OT2_Psalms']//chapter)[140]",
        "Children": []
      },
      {
        "IsVisible": true,
        "Book": "OT2_Psalms",
        "Name": "Psalms 141",
        "XPath": "(/html[1]/body[@book='OT2_Psalms']//chapter)[141]",
        "Children": []
      },
      {
        "IsVisible": true,
        "Book": "OT2_Psalms",
        "Name": "Psalms 142",
        "XPath": "(/html[1]/body[@book='OT2_Psalms']//chapter)[142]",
        "Children": []
      },
      {
        "IsVisible": true,
        "Book": "OT2_Psalms",
        "Name": "Psalms 143",
        "XPath": "(/html[1]/body[@book='OT2_Psalms']//chapter)[143]",
        "Children": []
      },
      {
        "IsVisible": true,
        "Book": "OT2_Psalms",
        "Name": "Psalms 144",
        "XPath": "(/html[1]/body[@book='OT2_Psalms']//chapter)[144]",
        "Children": []
      },
      {
        "IsVisible": true,
        "Book": "OT2_Psalms",
        "Name": "Psalms 145",
        "XPath": "(/html[1]/body[@book='OT2_Psalms']//chapter)[145]",
        "Children": []
      },
      {
        "IsVisible": true,
        "Book": "OT2_Psalms",
        "Name": "Psalms 146",
        "XPath": "(/html[1]/body[@book='OT2_Psalms']//chapter)[146]",
        "Children": []
      },
      {
        "IsVisible": true,
        "Book": "OT2_Psalms",
        "Name": "Psalms 147",
        "XPath": "(/html[1]/body[@book='OT2_Psalms']//chapter)[147]",
        "Children": []
      },
      {
        "IsVisible": true,
        "Book": "OT2_Psalms",
        "Name": "Psalms 148",
        "XPath": "(/html[1]/body[@book='OT2_Psalms']//chapter)[148]",
        "Children": []
      },
      {
        "IsVisible": true,
        "Book": "OT2_Psalms",
        "Name": "Psalms 149",
        "XPath": "(/html[1]/body[@book='OT2_Psalms']//chapter)[149]",
        "Children": []
      },
      {
        "IsVisible": true,
        "Book": "OT2_Psalms",
        "Name": "Psalms 150",
        "XPath": "(/html[1]/body[@book='OT2_Psalms']//chapter)[150]",
        "Children": []
      }
    ]
  },
  {
    "IsVisible": true,
    "Book": "OT2_Proverbs",
    "Name": "Proverbs",
    "XPath": "/html[1]/body[@book='OT2_Proverbs']/book",
    "Children": [
      {
        "IsVisible": true,
        "Book": "OT2_Proverbs",
        "Name": "Proverbs 1",
        "XPath": "(/html[1]/body[@book='OT2_Proverbs']//chapter)[1]",
        "Children": []
      },
      {
        "IsVisible": true,
        "Book": "OT2_Proverbs",
        "Name": "Proverbs 2",
        "XPath": "(/html[1]/body[@book='OT2_Proverbs']//chapter)[2]",
        "Children": []
      },
      {
        "IsVisible": true,
        "Book": "OT2_Proverbs",
        "Name": "Proverbs 3",
        "XPath": "(/html[1]/body[@book='OT2_Proverbs']//chapter)[3]",
        "Children": []
      },
      {
        "IsVisible": true,
        "Book": "OT2_Proverbs",
        "Name": "Proverbs 4",
        "XPath": "(/html[1]/body[@book='OT2_Proverbs']//chapter)[4]",
        "Children": []
      },
      {
        "IsVisible": true,
        "Book": "OT2_Proverbs",
        "Name": "Proverbs 5",
        "XPath": "(/html[1]/body[@book='OT2_Proverbs']//chapter)[5]",
        "Children": []
      },
      {
        "IsVisible": true,
        "Book": "OT2_Proverbs",
        "Name": "Proverbs 6",
        "XPath": "(/html[1]/body[@book='OT2_Proverbs']//chapter)[6]",
        "Children": []
      },
      {
        "IsVisible": true,
        "Book": "OT2_Proverbs",
        "Name": "Proverbs 7",
        "XPath": "(/html[1]/body[@book='OT2_Proverbs']//chapter)[7]",
        "Children": []
      },
      {
        "IsVisible": true,
        "Book": "OT2_Proverbs",
        "Name": "Proverbs 8",
        "XPath": "(/html[1]/body[@book='OT2_Proverbs']//chapter)[8]",
        "Children": []
      },
      {
        "IsVisible": true,
        "Book": "OT2_Proverbs",
        "Name": "Proverbs 9",
        "XPath": "(/html[1]/body[@book='OT2_Proverbs']//chapter)[9]",
        "Children": []
      },
      {
        "IsVisible": true,
        "Book": "OT2_Proverbs",
        "Name": "Proverbs 10",
        "XPath": "(/html[1]/body[@book='OT2_Proverbs']//chapter)[10]",
        "Children": []
      },
      {
        "IsVisible": true,
        "Book": "OT2_Proverbs",
        "Name": "Proverbs 11",
        "XPath": "(/html[1]/body[@book='OT2_Proverbs']//chapter)[11]",
        "Children": []
      },
      {
        "IsVisible": true,
        "Book": "OT2_Proverbs",
        "Name": "Proverbs 12",
        "XPath": "(/html[1]/body[@book='OT2_Proverbs']//chapter)[12]",
        "Children": []
      },
      {
        "IsVisible": true,
        "Book": "OT2_Proverbs",
        "Name": "Proverbs 13",
        "XPath": "(/html[1]/body[@book='OT2_Proverbs']//chapter)[13]",
        "Children": []
      },
      {
        "IsVisible": true,
        "Book": "OT2_Proverbs",
        "Name": "Proverbs 14",
        "XPath": "(/html[1]/body[@book='OT2_Proverbs']//chapter)[14]",
        "Children": []
      },
      {
        "IsVisible": true,
        "Book": "OT2_Proverbs",
        "Name": "Proverbs 15",
        "XPath": "(/html[1]/body[@book='OT2_Proverbs']//chapter)[15]",
        "Children": []
      },
      {
        "IsVisible": true,
        "Book": "OT2_Proverbs",
        "Name": "Proverbs 16",
        "XPath": "(/html[1]/body[@book='OT2_Proverbs']//chapter)[16]",
        "Children": []
      },
      {
        "IsVisible": true,
        "Book": "OT2_Proverbs",
        "Name": "Proverbs 17",
        "XPath": "(/html[1]/body[@book='OT2_Proverbs']//chapter)[17]",
        "Children": []
      },
      {
        "IsVisible": true,
        "Book": "OT2_Proverbs",
        "Name": "Proverbs 18",
        "XPath": "(/html[1]/body[@book='OT2_Proverbs']//chapter)[18]",
        "Children": []
      },
      {
        "IsVisible": true,
        "Book": "OT2_Proverbs",
        "Name": "Proverbs 19",
        "XPath": "(/html[1]/body[@book='OT2_Proverbs']//chapter)[19]",
        "Children": []
      },
      {
        "IsVisible": true,
        "Book": "OT2_Proverbs",
        "Name": "Proverbs 20",
        "XPath": "(/html[1]/body[@book='OT2_Proverbs']//chapter)[20]",
        "Children": []
      },
      {
        "IsVisible": true,
        "Book": "OT2_Proverbs",
        "Name": "Proverbs 21",
        "XPath": "(/html[1]/body[@book='OT2_Proverbs']//chapter)[21]",
        "Children": []
      },
      {
        "IsVisible": true,
        "Book": "OT2_Proverbs",
        "Name": "Proverbs 22",
        "XPath": "(/html[1]/body[@book='OT2_Proverbs']//chapter)[22]",
        "Children": []
      },
      {
        "IsVisible": true,
        "Book": "OT2_Proverbs",
        "Name": "Proverbs 23",
        "XPath": "(/html[1]/body[@book='OT2_Proverbs']//chapter)[23]",
        "Children": []
      },
      {
        "IsVisible": true,
        "Book": "OT2_Proverbs",
        "Name": "Proverbs 24",
        "XPath": "(/html[1]/body[@book='OT2_Proverbs']//chapter)[24]",
        "Children": []
      },
      {
        "IsVisible": true,
        "Book": "OT2_Proverbs",
        "Name": "Proverbs 25",
        "XPath": "(/html[1]/body[@book='OT2_Proverbs']//chapter)[25]",
        "Children": []
      },
      {
        "IsVisible": true,
        "Book": "OT2_Proverbs",
        "Name": "Proverbs 26",
        "XPath": "(/html[1]/body[@book='OT2_Proverbs']//chapter)[26]",
        "Children": []
      },
      {
        "IsVisible": true,
        "Book": "OT2_Proverbs",
        "Name": "Proverbs 27",
        "XPath": "(/html[1]/body[@book='OT2_Proverbs']//chapter)[27]",
        "Children": []
      },
      {
        "IsVisible": true,
        "Book": "OT2_Proverbs",
        "Name": "Proverbs 28",
        "XPath": "(/html[1]/body[@book='OT2_Proverbs']//chapter)[28]",
        "Children": []
      },
      {
        "IsVisible": true,
        "Book": "OT2_Proverbs",
        "Name": "Proverbs 29",
        "XPath": "(/html[1]/body[@book='OT2_Proverbs']//chapter)[29]",
        "Children": []
      },
      {
        "IsVisible": true,
        "Book": "OT2_Proverbs",
        "Name": "Proverbs 30",
        "XPath": "(/html[1]/body[@book='OT2_Proverbs']//chapter)[30]",
        "Children": []
      },
      {
        "IsVisible": true,
        "Book": "OT2_Proverbs",
        "Name": "Proverbs 31",
        "XPath": "(/html[1]/body[@book='OT2_Proverbs']//chapter)[31]",
        "Children": []
      }
    ]
  },
  {
    "IsVisible": true,
    "Book": "OT2_Ecclesiastes",
    "Name": "Ecclesiastes",
    "XPath": "/html[1]/body[@book='OT2_Ecclesiastes']/book",
    "Children": [
      {
        "IsVisible": true,
        "Book": "OT2_Ecclesiastes",
        "Name": "Ecclesiastes 1",
        "XPath": "(/html[1]/body[@book='OT2_Ecclesiastes']//chapter)[1]",
        "Children": []
      },
      {
        "IsVisible": true,
        "Book": "OT2_Ecclesiastes",
        "Name": "Ecclesiastes 2",
        "XPath": "(/html[1]/body[@book='OT2_Ecclesiastes']//chapter)[2]",
        "Children": []
      },
      {
        "IsVisible": true,
        "Book": "OT2_Ecclesiastes",
        "Name": "Ecclesiastes 3",
        "XPath": "(/html[1]/body[@book='OT2_Ecclesiastes']//chapter)[3]",
        "Children": []
      },
      {
        "IsVisible": true,
        "Book": "OT2_Ecclesiastes",
        "Name": "Ecclesiastes 4",
        "XPath": "(/html[1]/body[@book='OT2_Ecclesiastes']//chapter)[4]",
        "Children": []
      },
      {
        "IsVisible": true,
        "Book": "OT2_Ecclesiastes",
        "Name": "Ecclesiastes 5",
        "XPath": "(/html[1]/body[@book='OT2_Ecclesiastes']//chapter)[5]",
        "Children": []
      },
      {
        "IsVisible": true,
        "Book": "OT2_Ecclesiastes",
        "Name": "Ecclesiastes 6",
        "XPath": "(/html[1]/body[@book='OT2_Ecclesiastes']//chapter)[6]",
        "Children": []
      },
      {
        "IsVisible": true,
        "Book": "OT2_Ecclesiastes",
        "Name": "Ecclesiastes 7",
        "XPath": "(/html[1]/body[@book='OT2_Ecclesiastes']//chapter)[7]",
        "Children": []
      },
      {
        "IsVisible": true,
        "Book": "OT2_Ecclesiastes",
        "Name": "Ecclesiastes 8",
        "XPath": "(/html[1]/body[@book='OT2_Ecclesiastes']//chapter)[8]",
        "Children": []
      },
      {
        "IsVisible": true,
        "Book": "OT2_Ecclesiastes",
        "Name": "Ecclesiastes 9",
        "XPath": "(/html[1]/body[@book='OT2_Ecclesiastes']//chapter)[9]",
        "Children": []
      },
      {
        "IsVisible": true,
        "Book": "OT2_Ecclesiastes",
        "Name": "Ecclesiastes 10",
        "XPath": "(/html[1]/body[@book='OT2_Ecclesiastes']//chapter)[10]",
        "Children": []
      },
      {
        "IsVisible": true,
        "Book": "OT2_Ecclesiastes",
        "Name": "Ecclesiastes 11",
        "XPath": "(/html[1]/body[@book='OT2_Ecclesiastes']//chapter)[11]",
        "Children": []
      },
      {
        "IsVisible": true,
        "Book": "OT2_Ecclesiastes",
        "Name": "Ecclesiastes 12",
        "XPath": "(/html[1]/body[@book='OT2_Ecclesiastes']//chapter)[12]",
        "Children": []
      }
    ]
  }
]